{
  "version": 1,
  "updated_at": "2026-06-17T04:42:56Z",
  "count": 20,
  "pool_total": 38,
  "campaign_id": "main-landing",
  "source": "backlink_sync",
  "board_urls": 0,
  "keyword_coverage": {
    "강남 가라오케": 6,
    "강남 풀싸롱": 3,
    "강남 하이퍼블릭": 7,
    "강남 클럽": 1,
    "강남 유흥": 3
  },
  "tier_distribution": {
    "S": 1,
    "A": 9,
    "B": 10
  },
  "table_rows": [
    {
      "target_keyword": "강남 가라오케",
      "platform_type": "directory",
      "tier_hint": "S",
      "deploy_url": "https://roompang.com/",
      "entry_url": "https://roompang.com/",
      "dofollow_hint": true,
      "write_captcha": false,
      "signup_captcha": false,
      "trait_score": 100,
      "serp_rank": 1
    },
    {
      "target_keyword": "강남 가라오케",
      "platform_type": "profile",
      "tier_hint": "A",
      "deploy_url": "https://www.clickn.co.kr/",
      "entry_url": "https://www.clickn.co.kr/",
      "dofollow_hint": true,
      "write_captcha": false,
      "signup_captcha": false,
      "trait_score": 100,
      "serp_rank": 1
    },
    {
      "target_keyword": "강남 가라오케",
      "platform_type": "guide_hub",
      "tier_hint": "A",
      "deploy_url": "https://choicelounge.co.kr/",
      "entry_url": "https://choicelounge.co.kr/",
      "dofollow_hint": true,
      "write_captcha": false,
      "signup_captcha": false,
      "trait_score": 100,
      "serp_rank": 1
    },
    {
      "target_keyword": "강남 풀싸롱",
      "platform_type": "guide_hub",
      "tier_hint": "A",
      "deploy_url": "https://clicknn.co.kr/pages/gangnampoolsalon",
      "entry_url": "https://clicknn.co.kr/pages/gangnampoolsalon",
      "dofollow_hint": true,
      "write_captcha": false,
      "signup_captcha": false,
      "trait_score": 100,
      "serp_rank": 1
    },
    {
      "target_keyword": "강남 하이퍼블릭",
      "platform_type": "guide_hub",
      "tier_hint": "A",
      "deploy_url": "https://clicknn.co.kr/pages/gangnamhyperbolic",
      "entry_url": "https://clicknn.co.kr/pages/gangnamhyperbolic",
      "dofollow_hint": true,
      "write_captcha": false,
      "signup_captcha": false,
      "trait_score": 100,
      "serp_rank": 1
    },
    {
      "target_keyword": "강남 클럽",
      "platform_type": "guide_hub",
      "tier_hint": "A",
      "deploy_url": "https://aceclub.co.kr/gangnam-club-guide/",
      "entry_url": "https://aceclub.co.kr/gangnam-club-guide/",
      "dofollow_hint": true,
      "write_captcha": false,
      "signup_captcha": false,
      "trait_score": 100,
      "serp_rank": 1
    },
    {
      "target_keyword": "강남 가라오케",
      "platform_type": "profile",
      "tier_hint": "A",
      "deploy_url": "https://garaoke.clickn.co.kr/",
      "entry_url": "https://garaoke.clickn.co.kr/",
      "dofollow_hint": true,
      "write_captcha": false,
      "signup_captcha": false,
      "trait_score": 95,
      "serp_rank": 1
    },
    {
      "target_keyword": "강남 유흥",
      "platform_type": "guide_hub",
      "tier_hint": "A",
      "deploy_url": "https://www.gangnamworld.co.kr/guide.html",
      "entry_url": "https://www.gangnamworld.co.kr/guide.html",
      "dofollow_hint": true,
      "write_captcha": false,
      "signup_captcha": false,
      "trait_score": 100,
      "serp_rank": 2
    },
    {
      "target_keyword": "강남 하이퍼블릭",
      "platform_type": "guide_hub",
      "tier_hint": "A",
      "deploy_url": "https://choicelounge.co.kr/highpublic/index.html",
      "entry_url": "https://choicelounge.co.kr/highpublic/index.html",
      "dofollow_hint": true,
      "write_captcha": false,
      "signup_captcha": false,
      "trait_score": 100,
      "serp_rank": 3
    },
    {
      "target_keyword": "강남 하이퍼블릭",
      "platform_type": "guide_hub",
      "tier_hint": "A",
      "deploy_url": "http://choicelounge.co.kr/",
      "entry_url": "http://choicelounge.co.kr/",
      "dofollow_hint": true,
      "write_captcha": false,
      "signup_captcha": false,
      "trait_score": 100,
      "serp_rank": 4
    },
    {
      "target_keyword": "강남 가라오케",
      "platform_type": "web2",
      "tier_hint": "B",
      "deploy_url": "https://www.safetyreport.go.kr/",
      "entry_url": "https://www.safetyreport.go.kr/",
      "dofollow_hint": true,
      "write_captcha": false,
      "signup_captcha": false,
      "trait_score": 85,
      "serp_rank": 1
    },
    {
      "target_keyword": "강남 가라오케",
      "platform_type": "web2",
      "tier_hint": "B",
      "deploy_url": "https://gangnamkaraoke.co.kr/",
      "entry_url": "https://gangnamkaraoke.co.kr/",
      "dofollow_hint": true,
      "write_captcha": false,
      "signup_captcha": false,
      "trait_score": 85,
      "serp_rank": 1
    },
    {
      "target_keyword": "강남 풀싸롱",
      "platform_type": "web2",
      "tier_hint": "B",
      "deploy_url": "https://classicsalong.com/",
      "entry_url": "https://classicsalong.com/",
      "dofollow_hint": true,
      "write_captcha": false,
      "signup_captcha": false,
      "trait_score": 85,
      "serp_rank": 1
    },
    {
      "target_keyword": "강남 풀싸롱",
      "platform_type": "web2",
      "tier_hint": "B",
      "deploy_url": "https://applegangnam.com/",
      "entry_url": "https://applegangnam.com/",
      "dofollow_hint": true,
      "write_captcha": false,
      "signup_captcha": false,
      "trait_score": 85,
      "serp_rank": 1
    },
    {
      "target_keyword": "강남 하이퍼블릭",
      "platform_type": "web2",
      "tier_hint": "B",
      "deploy_url": "https://gangnamdalto.co.kr/",
      "entry_url": "https://gangnamdalto.co.kr/",
      "dofollow_hint": true,
      "write_captcha": false,
      "signup_captcha": false,
      "trait_score": 85,
      "serp_rank": 1
    },
    {
      "target_keyword": "강남 하이퍼블릭",
      "platform_type": "web2",
      "tier_hint": "B",
      "deploy_url": "https://gangnammirror.com/",
      "entry_url": "https://gangnammirror.com/",
      "dofollow_hint": true,
      "write_captcha": false,
      "signup_captcha": false,
      "trait_score": 85,
      "serp_rank": 1
    },
    {
      "target_keyword": "강남 하이퍼블릭",
      "platform_type": "web2",
      "tier_hint": "B",
      "deploy_url": "https://thesevensalon.com/",
      "entry_url": "https://thesevensalon.com/",
      "dofollow_hint": true,
      "write_captcha": false,
      "signup_captcha": false,
      "trait_score": 85,
      "serp_rank": 1
    },
    {
      "target_keyword": "강남 하이퍼블릭",
      "platform_type": "web2",
      "tier_hint": "B",
      "deploy_url": "https://gangnam-nightlife.co.kr/blog/0011.html",
      "entry_url": "https://gangnam-nightlife.co.kr/blog/0011.html",
      "dofollow_hint": true,
      "write_captcha": false,
      "signup_captcha": false,
      "trait_score": 85,
      "serp_rank": 1
    },
    {
      "target_keyword": "강남 유흥",
      "platform_type": "web2",
      "tier_hint": "B",
      "deploy_url": "https://www.korea.kr/",
      "entry_url": "https://www.korea.kr/",
      "dofollow_hint": true,
      "write_captcha": false,
      "signup_captcha": false,
      "trait_score": 85,
      "serp_rank": 1
    },
    {
      "target_keyword": "강남 유흥",
      "platform_type": "web2",
      "tier_hint": "B",
      "deploy_url": "https://gangnam-nightlife.co.kr/blog/0036.html",
      "entry_url": "https://gangnam-nightlife.co.kr/blog/0036.html",
      "dofollow_hint": true,
      "write_captcha": false,
      "signup_captcha": false,
      "trait_score": 85,
      "serp_rank": 1
    }
  ]
}
